CloudAtlas/DadosAbertos.py
CloudAtlas/Utils.py
cloudatlas-0.0.5.dist-info/LICENSE
cloudatlas-0.0.5.dist-info/WHEEL
cloudatlas-0.0.5.dist-info/METADATA
cloudatlas-0.0.5.dist-info/RECORD
